{
  "id": "feat.two_weapon_fighting",
  "name": "Two-Weapon Fighting",
  "chapter": 5,
  "status": "complete",
  "category": "Fighting Style",
  "repeatable": false,
  "prerequisites": [
    "Prerequisite: Fighting Style Feature"
  ],
  "benefits": [
    {
      "name": "Benefit",
      "action_type": "none",
      "trigger": "passive",
      "effects": [
        "When you make an extra attack as a result of using a weapon that has the Light property, you can add your ability modifier to the damage of that attack if you aren't already adding it to the damage."
      ]
    }
  ],
  "notes": [],
  "sourceRef": {
    "file": "docs/sources/phb2024/06-chapter 5/07-Feats - Player’s Handbook - Dungeons & Dragons - Sources - D&D Beyond.pdf",
    "pages": [
      19
    ],
    "section": "Two-Weapon Fighting"
  }
}
