{
    "id":  "dm_advice.dmg.chapter02.trying_again",
    "name":  "Trying Again",
    "chapter":  "dmg-2024.chapter-02",
    "status":  "complete",
    "guidance":  [
                     "Allow repeated attempts only if time, risk, or circumstances change.",
                     "Otherwise, treat the first result as final to keep the game moving.",
                     "Use consequences to make retries meaningful."
                 ],
    "tags":  [
                 "chapter-02",
                 "rules-adjudication"
             ],
    "sourceRef":  {
                      "file":  "docs/sources/dm-guide2024/Dungeon Master\u0027s Guide (2024) - 5etools.pdf",
                      "pages":  [
                                    29
                                ],
                      "section":  "Trying Again"
                  },
    "notes":  [

              ]
}
