{
  "id": "item.weapon.heavy_crossbow",
  "name": "Heavy Crossbow",
  "chapter": 6,
  "status": "complete",
  "item_type": "weapon",
  "weapon_category": "Martial",
  "weapon_type": "Ranged",
  "damage": "1d10",
  "damage_type": "Piercing",
  "properties": [
    "Ammunition (Range 100/400; Bolt)",
    "Heavy",
    "Loading",
    "Two-Handed"
  ],
  "mastery": "Push",
  "weight": "18 lb.",
  "cost": "50 GP",
  "sourceRef": {
    "file": "docs/sources/phb2024/08-chapter 6/08-Equipment - Player’s Handbook - Dungeons & Dragons - Sources - D&D Beyond.pdf",
    "pages": [
      2,
      3
    ],
    "section": "Weapons"
  },
  "notes": []
}
