{
  "id": "dm_advice.dmg.chapter05.shar",
  "name": "Shar",
  "chapter": "dmg-2024.chapter-05",
  "status": "complete",
  "guidance": [
    "Present Shar as a closed, secretive empire.",
    "Use spies and cult activity to extend its influence.",
    "Keep outsiders knowledge limited to rumors."
  ],
  "tags": [
    "chapter-05",
    "setting",
    "greyhawk",
    "region"
  ],
  "sourceRef": {
    "file": "docs/sources/dm-guide2024/Dungeon Master's Guide (2024) - 5etools.pdf",
    "pages": [
      146
    ],
    "section": "Shar"
  },
  "notes": []
}
