{
  "id": "spell.mind_sliver",
  "name": "Mind Sliver",
  "chapter": 7,
  "status": "complete",
  "level": 0,
  "school": "Enchantment",
  "classes": [
    "class.sorcerer",
    "class.warlock",
    "class.wizard"
  ],
  "casting_time": "Action",
  "range": "60 feet",
  "components": {
    "flags": [
      "V"
    ],
    "material": null
  },
  "duration": "1 round",
  "description": [
    "You try to temporarily sliver the mind of one creature you can see within range. The target must succeed on an Intelligence saving throw or take 1d6 Psychic damage and subtract 1d4 from the next saving throw it makes before the end of your next turn. Cantrip Upgrade. The damage increases by 1d6 when you reach levels 5 (2d6), 11 (3d6), and 17 (4d6)."
  ],
  "higher_level": null,
  "sourceRef": {
    "file": "docs/sources/phb2024/09-chapter7/10-Spell Descriptions - Player’s Handbook - Dungeons & Dragons - Sources - D&D Beyond.pdf",
    "pages": [
      93
    ],
    "section": "Spell Descriptions"
  },
  "notes": []
}
